betterdataclass/StrictDictionary.py
betterdataclass/StrictList.py
betterdataclass/__init__.py
betterdataclass/helper/__init__.py
betterdataclass/helper/initiate.py
betterdataclass/helper/to_dict.py
betterdataclass/helper/validate.py
betterdataclass-202.4.dist-info/LICENSE
betterdataclass-202.4.dist-info/METADATA
betterdataclass-202.4.dist-info/WHEEL
betterdataclass-202.4.dist-info/top_level.txt
betterdataclass-202.4.dist-info/RECORD
