Metadata-Version: 2.1
Name: betterdataclass
Version: 202.4
Summary: A multipurpose dataclass libarary used for validation and data structuring.
Home-page: https://github.com/dvnasutosh/betterdataclasses
Author: Asutosh Rath
Author-email: dvnasutosh@gmail.com
Classifier: Development Status :: 5 - Production/Stable
Classifier: Intended Audience :: Developers
Classifier: License :: OSI Approved :: MIT License
Classifier: Programming Language :: Python :: 3
Classifier: Programming Language :: Python :: 3.6
Classifier: Programming Language :: Python :: 3.7
Classifier: Programming Language :: Python :: 3.8
Classifier: Programming Language :: Python :: 3.9
Classifier: Topic :: Software Development :: Libraries :: Python Modules
Classifier: License :: OSI Approved :: GNU General Public License v3 (GPLv3)
License-File: LICENSE
